ms_marathon_api/__init__.py
ms_marathon_api/marathon/__init__.py
ms_marathon_api/marathon/__tests__/__init__.py
ms_marathon_api/marathon/__tests__/test_marathon.py
ms_marathon_api/marathon/api.py
ms_marathon_api/marathon/parsers/__init__.py
ms_marathon_api/marathon/parsers/parse_table1.py
ms_marathon_api/marathon/queries/__init__.py
ms_marathon_api/marathon/queries/bigquery.py
ms_marathon_api/marathon/queries/sql_server.py
ms_marathon_api/sql_server/__init__.py
ms_marathon_api/sql_server/__tests__/__init__.py
ms_marathon_api/sql_server/__tests__/test_sql_server.py
ms_marathon_api/sql_server/connection.py
ms_sqlserver_api-0.0.12.dist-info/LICENSE
ms_sqlserver_api-0.0.12.dist-info/METADATA
ms_sqlserver_api-0.0.12.dist-info/WHEEL
ms_sqlserver_api-0.0.12.dist-info/RECORD
